netlist.v
/* Generated by Yosys 0.66 (git sha1 7f8fdfd8d7bc08c749a2a969388d3425d4f369d5, x86_64-w64-mingw32-g++ 16.1.0 -march=nocona -msahf -mtune=generic -O2 -fstack-protector-strong -O3) */

module binary_to_gray(binary, gray);
  input [3:0] binary;
  wire [3:0] binary;
  output [3:0] gray;
  wire [3:0] gray;
  \$_XOR_  _0_ (
    .A(binary[0]),
    .B(binary[1]),
    .Y(gray[0])
  );
  \$_XOR_  _1_ (
    .A(binary[1]),
    .B(binary[2]),
    .Y(gray[1])
  );
  \$_XOR_  _2_ (
    .A(binary[2]),
    .B(binary[3]),
    .Y(gray[2])
  );
  assign gray[3] = binary[3];
endmodule

tb/design_tb.sv
`timescale 1ns/1ps

module binary_to_gray_tb;

    logic [3:0] binary;
    logic [3:0] gray;
    logic [3:0] expected_gray;
    integer i;
    integer errors;

    binary_to_gray dut (
        .binary(binary),
        .gray(gray)
    );

    initial begin
        $dumpfile("waveform.vcd");
        $dumpvars(0, binary_to_gray_tb);

        errors = 0;
        $display("Binary  Gray  Expected  Result");
        $display("------  ----  --------  ------");

        for (i = 0; i < 16; i = i + 1) begin
            binary = i[3:0];
            #10;
            expected_gray = binary ^ (binary >> 1);

            if (gray !== expected_gray) begin
                $display("%b    %b    %b      FAIL", binary, gray, expected_gray);
                errors = errors + 1;
            end else begin
                $display("%b    %b    %b      PASS", binary, gray, expected_gray);
            end
        end

        if (errors == 0)
            $display("\nAll 16 test cases PASSED.");
        else
            $display("\n%d test case(s) FAILED.", errors);

        $finish;
    end

endmodule

waveform.vcd
$date
	Sun Sep 13 10:20:43 2026
$end
$version
	Icarus Verilog
$end
$timescale
	1ps
$end
$scope module binary_to_gray_tb $end
$var wire 4 ! gray [3:0] $end
$var reg 4 " binary [3:0] $end
$var reg 4 # expected_gray [3:0] $end
$var integer 32 $ errors [31:0] $end
$var integer 32 % i [31:0] $end
$scope module dut $end
$var wire 4 & binary [3:0] $end
$var wire 4 ' gray [3:0] $end
$upscope $end
$upscope $end
$enddefinitions $end
$comment Show the parameter values. $end
$dumpall
$end
#0
$dumpvars
b0 '
b0 &
b0 %
b0 $
bx #
b0 "
b0 !
$end
#10000
b1 !
b1 '
b1 "
b1 &
b1 %
b0 #
#20000
b11 !
b11 '
b10 "
b10 &
b10 %
b1 #
#30000
b10 !
b10 '
b11 "
b11 &
b11 %
b11 #
#40000
b110 !
b110 '
b100 "
b100 &
b100 %
b10 #
#50000
b111 !
b111 '
b101 "
b101 &
b101 %
b110 #
#60000
b101 !
b101 '
b110 "
b110 &
b110 %
b111 #
#70000
b100 !
b100 '
b111 "
b111 &
b111 %
b101 #
#80000
b1100 !
b1100 '
b1000 "
b1000 &
b1000 %
b100 #
#90000
b1101 !
b1101 '
b1001 "
b1001 &
b1001 %
b1100 #
#100000
b1111 !
b1111 '
b1010 "
b1010 &
b1010 %
b1101 #
#110000
b1110 !
b1110 '
b1011 "
b1011 &
b1011 %
b1111 #
#120000
b1010 !
b1010 '
b1100 "
b1100 &
b1100 %
b1110 #
#130000
b1011 !
b1011 '
b1101 "
b1101 &
b1101 %
b1010 #
#140000
b1001 !
b1001 '
b1110 "
b1110 &
b1110 %
b1011 #
#150000
b1000 !
b1000 '
b1111 "
b1111 &
b1111 %
b1001 #
#160000
b10000 %
b1000 #
